bling_v2/__init__.py
bling_v2/__main__.py
bling_v2/controllers/__init__.py
bling_v2/controllers/bling_controller.py
bling_v2/logging_config.py
bling_v2/models/__init__.py
bling_v2/models/produto.py
bling_v2/utils/__init__.py
bling_v2/utils/telegram.py
bling_v2-0.1.7.dist-info/WHEEL
bling_v2-0.1.7.dist-info/METADATA
bling_v2-0.1.7.dist-info/RECORD
